coreason_connect/__init__.py
coreason_connect/app.py
coreason_connect/config.py
coreason_connect/interfaces.py
coreason_connect/loader.py
coreason_connect/main.py
coreason_connect/plugins/__init__.py
coreason_connect/plugins/gitops.py
coreason_connect/plugins/ms365.py
coreason_connect/secrets.py
coreason_connect/server.py
coreason_connect/types.py
coreason_connect/utils/__init__.py
coreason_connect/utils/logger.py
coreason_connect-0.3.0.dist-info/METADATA
coreason_connect-0.3.0.dist-info/WHEEL
coreason_connect-0.3.0.dist-info/licenses/LICENSE
coreason_connect-0.3.0.dist-info/licenses/NOTICE
coreason_connect-0.3.0.dist-info/RECORD
